mlfactory/__init__.py
mlfactory/applications/__init__.py
mlfactory/applications/deep_modular_scene_mapper/__init__.py
mlfactory/applications/deep_modular_scene_mapper/mapper.py
mlfactory/applications/deep_modular_scene_mapper/read_video.py
mlfactory/applications/deep_modular_scene_mapper/test_mapper.py
mlfactory/applications/deep_modular_scene_mapper/tools/__init__.py
mlfactory/applications/deep_modular_scene_mapper/tools/bundle_adjustment.py
mlfactory/applications/deep_modular_scene_mapper/tools/depth_estimator.py
mlfactory/applications/deep_modular_scene_mapper/tools/point_plane_icp.py
mlfactory/applications/deep_modular_scene_mapper/tools/pose_graph_optimizer.py
mlfactory/applications/deep_modular_scene_mapper/tools/project_rgbd.py
mlfactory/applications/deep_modular_scene_mapper/tools/rigid_transform_3D.py
mlfactory/applications/deep_modular_scene_mapper/tools/sift_matching.py
mlfactory/applications/multiview_sba_recon/__init__.py
mlfactory/applications/multiview_sba_recon/sfm.py
mlfactory/applications/multiview_sba_recon/disk_features/__init__.py
mlfactory/applications/multiview_sba_recon/disk_features/feature.py
mlfactory/applications/multiview_sba_recon/disk_features/disk/__init__.py
mlfactory/applications/multiview_sba_recon/disk_features/disk/train.py
mlfactory/applications/multiview_sba_recon/disk_features/disk/common/__init__.py
mlfactory/applications/multiview_sba_recon/disk_features/disk/common/errors.py
mlfactory/applications/multiview_sba_recon/disk_features/disk/common/image.py
mlfactory/applications/multiview_sba_recon/disk_features/disk/common/logger.py
mlfactory/applications/multiview_sba_recon/disk_features/disk/common/structs.py
mlfactory/applications/multiview_sba_recon/disk_features/disk/common/vis.py
mlfactory/applications/multiview_sba_recon/disk_features/disk/data/__init__.py
mlfactory/applications/multiview_sba_recon/disk_features/disk/data/datasets.py
mlfactory/applications/multiview_sba_recon/disk_features/disk/data/disk_dataset.py
mlfactory-0.1.1.dist-info/METADATA
mlfactory-0.1.1.dist-info/WHEEL
mlfactory-0.1.1.dist-info/top_level.txt
mlfactory-0.1.1.dist-info/RECORD
