Metadata-Version: 2.1
Name: mlfactory
Version: 0.1.1
Summary: Collection of several machine learning modules which can be applied to diverse projects
Home-page: https://github.com/Homagn/mlfactory
Author: Homagni Saha
Author-email: Homagni Saha <homagnisaha@gmail.com>
Project-URL: Homepage, https://github.com/Homagn/mlfactory
Classifier: Programming Language :: Python :: 3
Classifier: License :: OSI Approved :: MIT License
Classifier: Operating System :: OS Independent
Requires-Python: >=3.7
